{"type": "FeatureCollection", "features": [{"type": "Feature", "properties": {"speed": 33.603802709030745, "color": "#8e3a4f"}, "geometry": {"type": "Point", "coordinates": [-122.51569973954665, 37.941695979327584]}}, {"type": "Feature", "properties": {"speed": 33.4463150293486, "color": "#8d3b50"}, "geometry": {"type": "Point", "coordinates": [-122.51578192683257, 37.9413828677731]}}, {"type": "Feature", "properties": {"speed": 33.28725217621725, "color": "#8d3b50"}, "geometry": {"type": "Point", "coordinates": [-122.51586418874835, 37.94107746570701]}}, {"type": "Feature", "properties": {"speed": 33.14213666911385, "color": "#8c3b51"}, "geometry": {"type": "Point", "coordinates": [-122.51593939382597, 37.94080095375889]}}, {"type": "Feature", "properties": {"speed": 32.88085043409541, "color": "#8b3b52"}, "geometry": {"type": "Point", "coordinates": [-122.51602455463666, 37.940495806503534]}}, {"type": "Feature", "properties": {"speed": 32.47270034971156, "color": "#8a3c53"}, "geometry": {"type": "Point", "coordinates": [-122.51610305729673, 37.9402060988603]}}, {"type": "Feature", "properties": {"speed": 31.932716210120105, "color": "#883c55"}, "geometry": {"type": "Point", "coordinates": [-122.51617657925871, 37.93993256653683]}}, {"type": "Feature", "properties": {"speed": 31.594333907135987, "color": "#873d56"}, "geometry": {"type": "Point", "coordinates": [-122.51625536984803, 37.93964045025243]}}, {"type": "Feature", "properties": {"speed": 31.5868616, "color": "#873d56"}, "geometry": {"type": "Point", "coordinates": [-122.5163300142101, 37.939362700719485]}}, {"type": "Feature", "properties": {"speed": 31.050929015828917, "color": "#853d58"}, "geometry": {"type": "Point", "coordinates": [-122.51640185656403, 37.9390926087386]}}, {"type": "Feature", "properties": {"speed": 30.875532807889968, "color": "#843e58"}, "geometry": {"type": "Point", "coordinates": [-122.51647391542626, 37.938819629124964]}}, {"type": "Feature", "properties": {"speed": 30.6724989884982, "color": "#833e59"}, "geometry": {"type": "Point", "coordinates": [-122.51654819744117, 37.93854754496291]}}, {"type": "Feature", "properties": {"speed": 30.471677841428008, "color": "#833e5a"}, "geometry": {"type": "Point", "coordinates": [-122.51661992730048, 37.938284077581265]}}, {"type": "Feature", "properties": {"speed": 30.554319120101038, "color": "#833e59"}, "geometry": {"type": "Point", "coordinates": [-122.51669550162211, 37.9380020353223]}}, {"type": "Feature", "properties": {"speed": 30.40741278628786, "color": "#833e5a"}, "geometry": {"type": "Point", "coordinates": [-122.51676099008486, 37.937728545607065]}}, {"type": "Feature", "properties": {"speed": 30.593718112056784, "color": "#833e59"}, "geometry": {"type": "Point", "coordinates": [-122.51681156919476, 37.937470300810034]}}, {"type": "Feature", "properties": {"speed": 30.41184059141269, "color": "#833e5a"}, "geometry": {"type": "Point", "coordinates": [-122.51685504683583, 37.937186323487964]}}, {"type": "Feature", "properties": {"speed": 29.999460475651965, "color": "#813f5b"}, "geometry": {"type": "Point", "coordinates": [-122.51688233197623, 37.93690853626432]}}, {"type": "Feature", "properties": {"speed": 29.629708001118775, "color": "#803f5c"}, "geometry": {"type": "Point", "coordinates": [-122.5168941867834, 37.93663315128688]}}, {"type": "Feature", "properties": {"speed": 29.33250930982122, "color": "#7f405d"}, "geometry": {"type": "Point", "coordinates": [-122.51689245365779, 37.93637761154342]}}, {"type": "Feature", "properties": {"speed": 29.031909990174857, "color": "#7e405e"}, "geometry": {"type": "Point", "coordinates": [-122.51688075665695, 37.93612207441465]}}, {"type": "Feature", "properties": {"speed": 29.164985199843, "color": "#7e405e"}, "geometry": {"type": "Point", "coordinates": [-122.51685452771561, 37.9358530008746]}}, {"type": "Feature", "properties": {"speed": 29.068808701261556, "color": "#7e405e"}, "geometry": {"type": "Point", "coordinates": [-122.51681768308418, 37.935592659723056]}}, {"type": "Feature", "properties": {"speed": 29.268725343624027, "color": "#7f405e"}, "geometry": {"type": "Point", "coordinates": [-122.5167706957961, 37.935329420016366]}}, {"type": "Feature", "properties": {"speed": 28.91994978879357, "color": "#7d405f"}, "geometry": {"type": "Point", "coordinates": [-122.51672283161949, 37.93507215001603]}}, {"type": "Feature", "properties": {"speed": 28.618122808624676, "color": "#7c4060"}, "geometry": {"type": "Point", "coordinates": [-122.51667323360765, 37.93482319645482]}}, {"type": "Feature", "properties": {"speed": 28.855831739603545, "color": "#7d405f"}, "geometry": {"type": "Point", "coordinates": [-122.51662101425964, 37.9345595820547]}}, {"type": "Feature", "properties": {"speed": 29.060895305014775, "color": "#7e405e"}, "geometry": {"type": "Point", "coordinates": [-122.51657011111837, 37.93430417745331]}}, {"type": "Feature", "properties": {"speed": 29.166686483640657, "color": "#7e405e"}, "geometry": {"type": "Point", "coordinates": [-122.51652069461188, 37.93404413404437]}}, {"type": "Feature", "properties": {"speed": 29.72617239816666, "color": "#803f5c"}, "geometry": {"type": "Point", "coordinates": [-122.5164674631956, 37.93378119453517]}}, {"type": "Feature", "properties": {"speed": 29.98353137281292, "color": "#813f5b"}, "geometry": {"type": "Point", "coordinates": [-122.5164202301107, 37.93351949735988]}}, {"type": "Feature", "properties": {"speed": 30.42924212868101, "color": "#833e5a"}, "geometry": {"type": "Point", "coordinates": [-122.5163715342758, 37.93325614420596]}}, {"type": "Feature", "properties": {"speed": 30.354758255277787, "color": "#823e5a"}, "geometry": {"type": "Point", "coordinates": [-122.51631650106049, 37.93297706002479]}}, {"type": "Feature", "properties": {"speed": 30.55113752492734, "color": "#833e59"}, "geometry": {"type": "Point", "coordinates": [-122.51626184878805, 37.9327077071817]}}, {"type": "Feature", "properties": {"speed": 30.409900156484333, "color": "#833e5a"}, "geometry": {"type": "Point", "coordinates": [-122.51621047758196, 37.932437539759334]}}, {"type": "Feature", "properties": {"speed": 30.692955248056858, "color": "#843e59"}, "geometry": {"type": "Point", "coordinates": [-122.51616400189741, 37.932169412604324]}}, {"type": "Feature", "properties": {"speed": 30.66317282377082, "color": "#833e59"}, "geometry": {"type": "Point", "coordinates": [-122.51611499804758, 37.93189055413998]}}, {"type": "Feature", "properties": {"speed": 30.458522116148174, "color": "#833e5a"}, "geometry": {"type": "Point", "coordinates": [-122.51606486487849, 37.93160989214277]}}, {"type": "Feature", "properties": {"speed": 30.353575731709462, "color": "#823e5a"}, "geometry": {"type": "Point", "coordinates": [-122.51601552621177, 37.93133753990227]}}, {"type": "Feature", "properties": {"speed": 30.352196, "color": "#823e5a"}, "geometry": {"type": "Point", "coordinates": [-122.5159674118236, 37.931067425325246]}}, {"type": "Feature", "properties": {"speed": 30.352196, "color": "#823e5a"}, "geometry": {"type": "Point", "coordinates": [-122.51591805953596, 37.93079717838355]}}, {"type": "Feature", "properties": {"speed": 30.751386696211743, "color": "#843e59"}, "geometry": {"type": "Point", "coordinates": [-122.51586887849155, 37.930527935315254]}}, {"type": "Feature", "properties": {"speed": 30.668299158486928, "color": "#833e59"}, "geometry": {"type": "Point", "coordinates": [-122.51582226519655, 37.93026546183085]}}, {"type": "Feature", "properties": {"speed": 30.711463665568502, "color": "#843e59"}, "geometry": {"type": "Point", "coordinates": [-122.51576994651262, 37.92997623901184]}}, {"type": "Feature", "properties": {"speed": 30.661672543717746, "color": "#833e59"}, "geometry": {"type": "Point", "coordinates": [-122.51572065891975, 37.92970232740487]}}, {"type": "Feature", "properties": {"speed": 30.660862400000003, "color": "#833e59"}, "geometry": {"type": "Point", "coordinates": [-122.5156715297695, 37.92943640985237]}}, {"type": "Feature", "properties": {"speed": 30.763328972854676, "color": "#843e59"}, "geometry": {"type": "Point", "coordinates": [-122.51561922322072, 37.92915200665914]}}, {"type": "Feature", "properties": {"speed": 31.015000305620255, "color": "#853e58"}, "geometry": {"type": "Point", "coordinates": [-122.51556905440935, 37.928881894614626]}}, {"type": "Feature", "properties": {"speed": 30.92252296222547, "color": "#843e58"}, "geometry": {"type": "Point", "coordinates": [-122.51551694573565, 37.928611741378624]}}, {"type": "Feature", "properties": {"speed": 30.769887954373356, "color": "#843e59"}, "geometry": {"type": "Point", "coordinates": [-122.51546102076476, 37.92833664904423]}}, {"type": "Feature", "properties": {"speed": 30.763751199999998, "color": "#843e59"}, "geometry": {"type": "Point", "coordinates": [-122.51539934591419, 37.928061276254155]}}, {"type": "Feature", "properties": {"speed": 30.608882376211607, "color": "#833e59"}, "geometry": {"type": "Point", "coordinates": [-122.51533072153116, 37.92778113491504]}}, {"type": "Feature", "properties": {"speed": 30.30592945829709, "color": "#823e5a"}, "geometry": {"type": "Point", "coordinates": [-122.5152580585709, 37.92751807929506]}}, {"type": "Feature", "properties": {"speed": 29.939930614559433, "color": "#813f5b"}, "geometry": {"type": "Point", "coordinates": [-122.51517340681414, 37.92724905449458]}}, {"type": "Feature", "properties": {"speed": 29.79257312535479, "color": "#803f5c"}, "geometry": {"type": "Point", "coordinates": [-122.51508836587435, 37.927000997202335]}}, {"type": "Feature", "properties": {"speed": 30.088319336975907, "color": "#813f5b"}, "geometry": {"type": "Point", "coordinates": [-122.51499192860194, 37.9267368708117]}}, {"type": "Feature", "properties": {"speed": 30.54558864765346, "color": "#833e59"}, "geometry": {"type": "Point", "coordinates": [-122.51489216897112, 37.92647679451711]}}, {"type": "Feature", "properties": {"speed": 30.756380464251453, "color": "#843e59"}, "geometry": {"type": "Point", "coordinates": [-122.51478774616194, 37.92621575436068]}}, {"type": "Feature", "properties": {"speed": 30.66160568149333, "color": "#833e59"}, "geometry": {"type": "Point", "coordinates": [-122.51467102186456, 37.92594640794244]}}, {"type": "Feature", "properties": {"speed": 31.104811071508223, "color": "#853d58"}, "geometry": {"type": "Point", "coordinates": [-122.51454856946515, 37.925694911184635]}}, {"type": "Feature", "properties": {"speed": 31.0731525109223, "color": "#853d58"}, "geometry": {"type": "Point", "coordinates": [-122.51441295640522, 37.925427388525456]}}, {"type": "Feature", "properties": {"speed": 31.022207651920503, "color": "#853e58"}, "geometry": {"type": "Point", "coordinates": [-122.51427619915937, 37.925171629860735]}}, {"type": "Feature", "properties": {"speed": 31.07172005673109, "color": "#853d58"}, "geometry": {"type": "Point", "coordinates": [-122.5141318058537, 37.92491232905656]}}, {"type": "Feature", "properties": {"speed": 30.66160025729257, "color": "#833e59"}, "geometry": {"type": "Point", "coordinates": [-122.5139869067662, 37.92465439036102]}}, {"type": "Feature", "properties": {"speed": 30.41730479906894, "color": "#833e5a"}, "geometry": {"type": "Point", "coordinates": [-122.51385334549683, 37.924415036261095]}}, {"type": "Feature", "properties": {"speed": 30.50527132366088, "color": "#833e5a"}, "geometry": {"type": "Point", "coordinates": [-122.51370965257561, 37.92415245077564]}}, {"type": "Feature", "properties": {"speed": 30.1507173561634, "color": "#823f5b"}, "geometry": {"type": "Point", "coordinates": [-122.51357312912141, 37.923900918444254]}}, {"type": "Feature", "properties": {"speed": 29.947208738472874, "color": "#813f5b"}, "geometry": {"type": "Point", "coordinates": [-122.51344093796108, 37.92365676735456]}}, {"type": "Feature", "properties": {"speed": 29.652099035603545, "color": "#803f5c"}, "geometry": {"type": "Point", "coordinates": [-122.51331127647362, 37.92341815443597]}}, {"type": "Feature", "properties": {"speed": 29.731388655439794, "color": "#803f5c"}, "geometry": {"type": "Point", "coordinates": [-122.51317436291066, 37.923164035881705]}}, {"type": "Feature", "properties": {"speed": 29.68395014836747, "color": "#803f5c"}, "geometry": {"type": "Point", "coordinates": [-122.51303921371881, 37.92291201008316]}}, {"type": "Feature", "properties": {"speed": 29.633742114973256, "color": "#803f5c"}, "geometry": {"type": "Point", "coordinates": [-122.51291112606182, 37.92267177478924]}}, {"type": "Feature", "properties": {"speed": 29.6780197493791, "color": "#803f5c"}, "geometry": {"type": "Point", "coordinates": [-122.51278864897634, 37.92244310434439]}}, {"type": "Feature", "properties": {"speed": 29.63375642834116, "color": "#803f5c"}, "geometry": {"type": "Point", "coordinates": [-122.51264706734541, 37.922180094354225]}}, {"type": "Feature", "properties": {"speed": 29.68259405123205, "color": "#803f5c"}, "geometry": {"type": "Point", "coordinates": [-122.51251204195523, 37.921929871556635]}}, {"type": "Feature", "properties": {"speed": 29.880177474080632, "color": "#813f5c"}, "geometry": {"type": "Point", "coordinates": [-122.51238220402819, 37.921690237061426]}}, {"type": "Feature", "properties": {"speed": 30.087755296841422, "color": "#813f5b"}, "geometry": {"type": "Point", "coordinates": [-122.5122451208965, 37.92144043876136]}}, {"type": "Feature", "properties": {"speed": 30.12408413833595, "color": "#823f5b"}, "geometry": {"type": "Point", "coordinates": [-122.5120972020123, 37.921175702239104]}}, {"type": "Feature", "properties": {"speed": 31.0209732, "color": "#853e58"}, "geometry": {"type": "Point", "coordinates": [-122.51196011540955, 37.920922047010606]}}, {"type": "Feature", "properties": {"speed": 31.025409103905254, "color": "#853e58"}, "geometry": {"type": "Point", "coordinates": [-122.51183024267068, 37.92066267015463]}}, {"type": "Feature", "properties": {"speed": 31.171025081871335, "color": "#853d57"}, "geometry": {"type": "Point", "coordinates": [-122.51171620293152, 37.920413849030446]}}, {"type": "Feature", "properties": {"speed": 31.478404162652385, "color": "#863d56"}, "geometry": {"type": "Point", "coordinates": [-122.51160540731475, 37.92014241908282]}}, {"type": "Feature", "properties": {"speed": 31.78237425614513, "color": "#873d55"}, "geometry": {"type": "Point", "coordinates": [-122.51151107703612, 37.91987182479474]}}, {"type": "Feature", "properties": {"speed": 31.74271493970243, "color": "#873d55"}, "geometry": {"type": "Point", "coordinates": [-122.51142858181943, 37.91959207312146]}}, {"type": "Feature", "properties": {"speed": 31.877406318890646, "color": "#883c55"}, "geometry": {"type": "Point", "coordinates": [-122.51136687194669, 37.919335283870794]}}, {"type": "Feature", "properties": {"speed": 31.845406781677603, "color": "#883c55"}, "geometry": {"type": "Point", "coordinates": [-122.51130388783419, 37.91902600846141]}}, {"type": "Feature", "properties": {"speed": 32.038072466601754, "color": "#883c55"}, "geometry": {"type": "Point", "coordinates": [-122.5112588329362, 37.9187494940343]}}, {"type": "Feature", "properties": {"speed": 32.24824890798985, "color": "#893c54"}, "geometry": {"type": "Point", "coordinates": [-122.51121789297292, 37.91845505822745]}}, {"type": "Feature", "properties": {"speed": 32.799556416294514, "color": "#8b3b52"}, "geometry": {"type": "Point", "coordinates": [-122.51119434362886, 37.918162771439256]}}, {"type": "Feature", "properties": {"speed": 33.07207612140311, "color": "#8c3b51"}, "geometry": {"type": "Point", "coordinates": [-122.51118047880598, 37.91786163380768]}}, {"type": "Feature", "properties": {"speed": 33.33345653090894, "color": "#8d3b50"}, "geometry": {"type": "Point", "coordinates": [-122.51118511745949, 37.91755676702596]}}, {"type": "Feature", "properties": {"speed": 33.28808542544212, "color": "#8d3b50"}, "geometry": {"type": "Point", "coordinates": [-122.51120249554022, 37.917273934016606]}}, {"type": "Feature", "properties": {"speed": 33.48401604656544, "color": "#8d3a50"}, "geometry": {"type": "Point", "coordinates": [-122.5112378914999, 37.91696160626108]}}, {"type": "Feature", "properties": {"speed": 33.44118374345585, "color": "#8d3b50"}, "geometry": {"type": "Point", "coordinates": [-122.51128877696509, 37.91666658830563]}}, {"type": "Feature", "properties": {"speed": 33.38913455568267, "color": "#8d3b50"}, "geometry": {"type": "Point", "coordinates": [-122.51135038506406, 37.9163655556176]}}, {"type": "Feature", "properties": {"speed": 32.545599326057314, "color": "#8a3c53"}, "geometry": {"type": "Point", "coordinates": [-122.51142708028746, 37.91607636037382]}}, {"type": "Feature", "properties": {"speed": 32.01384328040832, "color": "#883c55"}, "geometry": {"type": "Point", "coordinates": [-122.51151246679719, 37.915790743734156]}}, {"type": "Feature", "properties": {"speed": 32.338025911878255, "color": "#893c54"}, "geometry": {"type": "Point", "coordinates": [-122.51159436015375, 37.915514984418664]}}, {"type": "Feature", "properties": {"speed": 32.06145755539784, "color": "#883c54"}, "geometry": {"type": "Point", "coordinates": [-122.51168490258264, 37.91522818238319]}}, {"type": "Feature", "properties": {"speed": 30.99314236929023, "color": "#853e58"}, "geometry": {"type": "Point", "coordinates": [-122.5117696966498, 37.91494861122869]}}, {"type": "Feature", "properties": {"speed": 30.619227724211953, "color": "#833e59"}, "geometry": {"type": "Point", "coordinates": [-122.51184951573785, 37.9146809602139]}}, {"type": "Feature", "properties": {"speed": 30.061595309417825, "color": "#813f5b"}, "geometry": {"type": "Point", "coordinates": [-122.51193137261289, 37.914418464768545]}}, {"type": "Feature", "properties": {"speed": 29.742565326796484, "color": "#803f5c"}, "geometry": {"type": "Point", "coordinates": [-122.51201965788631, 37.91415748030371]}}, {"type": "Feature", "properties": {"speed": 29.541159399752722, "color": "#7f3f5d"}, "geometry": {"type": "Point", "coordinates": [-122.51210228630468, 37.91390879780417]}}, {"type": "Feature", "properties": {"speed": 29.229761618520467, "color": "#7e405e"}, "geometry": {"type": "Point", "coordinates": [-122.51218478166344, 37.913645997877786]}}, {"type": "Feature", "properties": {"speed": 29.27122194714491, "color": "#7f405e"}, "geometry": {"type": "Point", "coordinates": [-122.51226659719134, 37.91338718786195]}}, {"type": "Feature", "properties": {"speed": 29.2718636, "color": "#7f405e"}, "geometry": {"type": "Point", "coordinates": [-122.51234482321613, 37.91314414979036]}}, {"type": "Feature", "properties": {"speed": 29.320962032750472, "color": "#7f405d"}, "geometry": {"type": "Point", "coordinates": [-122.51242742057094, 37.91288554669535]}}, {"type": "Feature", "properties": {"speed": 29.524190792625536, "color": "#7f3f5d"}, "geometry": {"type": "Point", "coordinates": [-122.51251158956451, 37.91262496605121]}}, {"type": "Feature", "properties": {"speed": 29.916206923034384, "color": "#813f5b"}, "geometry": {"type": "Point", "coordinates": [-122.51259340951903, 37.91237598220507]}}, {"type": "Feature", "properties": {"speed": 29.540154822873404, "color": "#7f3f5d"}, "geometry": {"type": "Point", "coordinates": [-122.51268476431743, 37.91211041632778]}}, {"type": "Feature", "properties": {"speed": 28.882842029018022, "color": "#7d405f"}, "geometry": {"type": "Point", "coordinates": [-122.51277469734391, 37.91186058672033]}}, {"type": "Feature", "properties": {"speed": 28.658538917293214, "color": "#7c4060"}, "geometry": {"type": "Point", "coordinates": [-122.51286704287845, 37.911609486475164]}}, {"type": "Feature", "properties": {"speed": 28.50234894216917, "color": "#7c4160"}, "geometry": {"type": "Point", "coordinates": [-122.51295974787044, 37.911362309453246]}}, {"type": "Feature", "properties": {"speed": 28.019218426422466, "color": "#7a4162"}, "geometry": {"type": "Point", "coordinates": [-122.51304846669645, 37.911132111325976]}}, {"type": "Feature", "properties": {"speed": 27.780647610793817, "color": "#794262"}, "geometry": {"type": "Point", "coordinates": [-122.51314618328406, 37.9108790768861]}}, {"type": "Feature", "properties": {"speed": 28.030984663345908, "color": "#7a4162"}, "geometry": {"type": "Point", "coordinates": [-122.51323866810652, 37.910645056910305]}}, {"type": "Feature", "properties": {"speed": 28.24049733326877, "color": "#7b4161"}, "geometry": {"type": "Point", "coordinates": [-122.51333613961617, 37.91040192676577]}}, {"type": "Feature", "properties": {"speed": 28.646586017738496, "color": "#7c4060"}, "geometry": {"type": "Point", "coordinates": [-122.51343536957069, 37.91016065889687]}}, {"type": "Feature", "properties": {"speed": 28.60404129592005, "color": "#7c4060"}, "geometry": {"type": "Point", "coordinates": [-122.5135390587936, 37.909916397579536]}}, {"type": "Feature", "properties": {"speed": 28.850761439488135, "color": "#7d405f"}, "geometry": {"type": "Point", "coordinates": [-122.51364276020962, 37.90967624886507]}}, {"type": "Feature", "properties": {"speed": 29.458552852591488, "color": "#7f3f5d"}, "geometry": {"type": "Point", "coordinates": [-122.51375106932787, 37.90942696420486]}}, {"type": "Feature", "properties": {"speed": 29.677163213789463, "color": "#803f5c"}, "geometry": {"type": "Point", "coordinates": [-122.51385717762722, 37.90917709385587]}}, {"type": "Feature", "properties": {"speed": 30.19580613707013, "color": "#823f5b"}, "geometry": {"type": "Point", "coordinates": [-122.51396997683804, 37.90891620004975]}}, {"type": "Feature", "properties": {"speed": 30.699265559700173, "color": "#843e59"}, "geometry": {"type": "Point", "coordinates": [-122.51407896016995, 37.90866274902608]}}, {"type": "Feature", "properties": {"speed": 31.466596076002034, "color": "#863d56"}, "geometry": {"type": "Point", "coordinates": [-122.5141915708025, 37.90839645019474]}}, {"type": "Feature", "properties": {"speed": 31.986174740099784, "color": "#883c55"}, "geometry": {"type": "Point", "coordinates": [-122.51430789276685, 37.90812541119558]}}, {"type": "Feature", "properties": {"speed": 32.19906939867917, "color": "#893c54"}, "geometry": {"type": "Point", "coordinates": [-122.51442642663118, 37.90785133532422]}}, {"type": "Feature", "properties": {"speed": 32.25331611422545, "color": "#893c54"}, "geometry": {"type": "Point", "coordinates": [-122.51454409271412, 37.90758135909943]}}, {"type": "Feature", "properties": {"speed": 32.50853593537313, "color": "#8a3c53"}, "geometry": {"type": "Point", "coordinates": [-122.51466831833937, 37.90729667239213]}}, {"type": "Feature", "properties": {"speed": 32.46308854378487, "color": "#8a3c53"}, "geometry": {"type": "Point", "coordinates": [-122.51478875539735, 37.90702343975013]}}, {"type": "Feature", "properties": {"speed": 32.71184445082655, "color": "#8b3b52"}, "geometry": {"type": "Point", "coordinates": [-122.51491193286145, 37.9067432239477]}}, {"type": "Feature", "properties": {"speed": 32.81592194825992, "color": "#8b3b52"}, "geometry": {"type": "Point", "coordinates": [-122.51502905470295, 37.90647000184583]}}, {"type": "Feature", "properties": {"speed": 33.4220474747782, "color": "#8d3b50"}, "geometry": {"type": "Point", "coordinates": [-122.51514540950723, 37.906175921062136]}}, {"type": "Feature", "properties": {"speed": 33.838052785955384, "color": "#8e3a4f"}, "geometry": {"type": "Point", "coordinates": [-122.51524633630395, 37.905883934051374]}}, {"type": "Feature", "properties": {"speed": 34.203483408411685, "color": "#903a4d"}, "geometry": {"type": "Point", "coordinates": [-122.51533793337491, 37.905582225908]}}, {"type": "Feature", "properties": {"speed": 34.63640658330385, "color": "#91394c"}, "geometry": {"type": "Point", "coordinates": [-122.51541156932683, 37.905295927389425]}}, {"type": "Feature", "properties": {"speed": 34.55950808290269, "color": "#91394c"}, "geometry": {"type": "Point", "coordinates": [-122.5154740418015, 37.90504534429142]}}, {"type": "Feature", "properties": {"speed": 34.56695208974144, "color": "#91394c"}, "geometry": {"type": "Point", "coordinates": [-122.51554240878232, 37.90467766447869]}}, {"type": "Feature", "properties": {"speed": 34.67124463877728, "color": "#91394c"}, "geometry": {"type": "Point", "coordinates": [-122.51558449726498, 37.904350595316885]}}, {"type": "Feature", "properties": {"speed": 34.52130832159625, "color": "#91394c"}, "geometry": {"type": "Point", "coordinates": [-122.5156175854705, 37.90403607594763]}}, {"type": "Feature", "properties": {"speed": 34.35234790373367, "color": "#90394d"}, "geometry": {"type": "Point", "coordinates": [-122.51564543470148, 37.90371405365558]}}, {"type": "Feature", "properties": {"speed": 33.839652034914174, "color": "#8e3a4f"}, "geometry": {"type": "Point", "coordinates": [-122.51567007794851, 37.90343554872408]}}, {"type": "Feature", "properties": {"speed": 33.581501258641936, "color": "#8e3a50"}, "geometry": {"type": "Point", "coordinates": [-122.51570059015259, 37.90310461282313]}}, {"type": "Feature", "properties": {"speed": 32.711804864715596, "color": "#8b3b52"}, "geometry": {"type": "Point", "coordinates": [-122.51572998519521, 37.90280231087597]}}, {"type": "Feature", "properties": {"speed": 32.37034347726624, "color": "#893c53"}, "geometry": {"type": "Point", "coordinates": [-122.51576005931963, 37.90252303083036]}}, {"type": "Feature", "properties": {"speed": 31.84456358701571, "color": "#883c55"}, "geometry": {"type": "Point", "coordinates": [-122.5157850942586, 37.90222160580654]}}, {"type": "Feature", "properties": {"speed": 31.31796328299294, "color": "#863d57"}, "geometry": {"type": "Point", "coordinates": [-122.51581362401093, 37.901924491957146]}}, {"type": "Feature", "properties": {"speed": 30.90350817241432, "color": "#843e58"}, "geometry": {"type": "Point", "coordinates": [-122.51583991463104, 37.90169526138175]}}, {"type": "Feature", "properties": {"speed": 30.413286218839218, "color": "#833e5a"}, "geometry": {"type": "Point", "coordinates": [-122.51586833206053, 37.901406847797254]}}, {"type": "Feature", "properties": {"speed": 30.94387545768655, "color": "#843e58"}, "geometry": {"type": "Point", "coordinates": [-122.51589433942863, 37.901105231636706]}}, {"type": "Feature", "properties": {"speed": 30.71513275262308, "color": "#843e59"}, "geometry": {"type": "Point", "coordinates": [-122.51591356396696, 37.90081850734158]}}, {"type": "Feature", "properties": {"speed": 30.90493502655754, "color": "#843e58"}, "geometry": {"type": "Point", "coordinates": [-122.51593623304511, 37.900554949221586]}}, {"type": "Feature", "properties": {"speed": 30.715900186600898, "color": "#843e59"}, "geometry": {"type": "Point", "coordinates": [-122.51596077442034, 37.900263775600884]}}, {"type": "Feature", "properties": {"speed": 30.666008082220113, "color": "#833e59"}, "geometry": {"type": "Point", "coordinates": [-122.51598273775501, 37.90000956335695]}}, {"type": "Feature", "properties": {"speed": 30.761918806542212, "color": "#843e59"}, "geometry": {"type": "Point", "coordinates": [-122.516009786316, 37.89970840815228]}}, {"type": "Feature", "properties": {"speed": 31.065319143790664, "color": "#853d58"}, "geometry": {"type": "Point", "coordinates": [-122.51603456070359, 37.89942975894285]}}, {"type": "Feature", "properties": {"speed": 31.498373094024096, "color": "#863d56"}, "geometry": {"type": "Point", "coordinates": [-122.51605811777671, 37.89916240720129]}}, {"type": "Feature", "properties": {"speed": 31.839249934863155, "color": "#883d55"}, "geometry": {"type": "Point", "coordinates": [-122.51608572591661, 37.89885875317246]}}, {"type": "Feature", "properties": {"speed": 31.892950890729722, "color": "#883c55"}, "geometry": {"type": "Point", "coordinates": [-122.51610883606187, 37.89858170810503]}}, {"type": "Feature", "properties": {"speed": 32.34845261983152, "color": "#893c54"}, "geometry": {"type": "Point", "coordinates": [-122.516132190464, 37.89828388836147]}}, {"type": "Feature", "properties": {"speed": 32.7085173779835, "color": "#8b3b52"}, "geometry": {"type": "Point", "coordinates": [-122.51615770962187, 37.89799095538801]}}, {"type": "Feature", "properties": {"speed": 32.869947707965814, "color": "#8b3b52"}, "geometry": {"type": "Point", "coordinates": [-122.51618233891745, 37.89769325059993]}}, {"type": "Feature", "properties": {"speed": 32.6259247463717, "color": "#8a3c53"}, "geometry": {"type": "Point", "coordinates": [-122.51620319404786, 37.897404696486994]}}, {"type": "Feature", "properties": {"speed": 32.80652912228976, "color": "#8b3b52"}, "geometry": {"type": "Point", "coordinates": [-122.51622425989466, 37.89711995279239]}}, {"type": "Feature", "properties": {"speed": 32.473548152922845, "color": "#8a3c53"}, "geometry": {"type": "Point", "coordinates": [-122.51624797852317, 37.896814548935]}}, {"type": "Feature", "properties": {"speed": 31.715953729426268, "color": "#873d56"}, "geometry": {"type": "Point", "coordinates": [-122.51627459165486, 37.89652589824264]}}, {"type": "Feature", "properties": {"speed": 31.262241355586266, "color": "#853d57"}, "geometry": {"type": "Point", "coordinates": [-122.51630830957777, 37.89625500839764]}}, {"type": "Feature", "properties": {"speed": 30.68730801081935, "color": "#833e59"}, "geometry": {"type": "Point", "coordinates": [-122.5163487350468, 37.89596869050095]}}, {"type": "Feature", "properties": {"speed": 30.156854059713147, "color": "#823f5b"}, "geometry": {"type": "Point", "coordinates": [-122.51639289067906, 37.89568880972991]}}, {"type": "Feature", "properties": {"speed": 30.1464184, "color": "#823f5b"}, "geometry": {"type": "Point", "coordinates": [-122.51643512827954, 37.89543327639154]}}, {"type": "Feature", "properties": {"speed": 29.899413243050024, "color": "#813f5b"}, "geometry": {"type": "Point", "coordinates": [-122.51648002880249, 37.89515511667387]}}, {"type": "Feature", "properties": {"speed": 29.236682807331547, "color": "#7e405e"}, "geometry": {"type": "Point", "coordinates": [-122.51652079352442, 37.89488550370435]}}, {"type": "Feature", "properties": {"speed": 28.625755665850967, "color": "#7c4060"}, "geometry": {"type": "Point", "coordinates": [-122.51654700456848, 37.894628228282386]}}, {"type": "Feature", "properties": {"speed": 28.306229195240135, "color": "#7b4161"}, "geometry": {"type": "Point", "coordinates": [-122.51656920511894, 37.894372076214]}}, {"type": "Feature", "properties": {"speed": 27.863567225720868, "color": "#7a4162"}, "geometry": {"type": "Point", "coordinates": [-122.51658771528919, 37.89412711204437]}}, {"type": "Feature", "properties": {"speed": 27.472662343282952, "color": "#784263"}, "geometry": {"type": "Point", "coordinates": [-122.5166026611147, 37.89389264086324]}}, {"type": "Feature", "properties": {"speed": 27.08579083820107, "color": "#774265"}, "geometry": {"type": "Point", "coordinates": [-122.516622648562, 37.8936335541506]}}, {"type": "Feature", "properties": {"speed": 26.857722010655205, "color": "#764365"}, "geometry": {"type": "Point", "coordinates": [-122.5166453223272, 37.89337789447538]}}, {"type": "Feature", "properties": {"speed": 26.554795818974824, "color": "#754366"}, "geometry": {"type": "Point", "coordinates": [-122.51666505359667, 37.89314045474911]}}, {"type": "Feature", "properties": {"speed": 26.152250494357165, "color": "#744468"}, "geometry": {"type": "Point", "coordinates": [-122.51668346261783, 37.892906606025115]}}, {"type": "Feature", "properties": {"speed": 25.78825017969546, "color": "#724469"}, "geometry": {"type": "Point", "coordinates": [-122.51669913935217, 37.8926718086214]}}, {"type": "Feature", "properties": {"speed": 25.227921282748706, "color": "#70456b"}, "geometry": {"type": "Point", "coordinates": [-122.5167153411657, 37.89244128474167]}}, {"type": "Feature", "properties": {"speed": 25.207756, "color": "#70456b"}, "geometry": {"type": "Point", "coordinates": [-122.51673146587488, 37.89221085445497]}}, {"type": "Feature", "properties": {"speed": 25.006238015791368, "color": "#70456b"}, "geometry": {"type": "Point", "coordinates": [-122.51674856200505, 37.891985223391366]}}, {"type": "Feature", "properties": {"speed": 24.554870942371057, "color": "#6e456d"}, "geometry": {"type": "Point", "coordinates": [-122.51676855207234, 37.89176562278087]}}, {"type": "Feature", "properties": {"speed": 23.806038630945906, "color": "#6b466f"}, "geometry": {"type": "Point", "coordinates": [-122.51679242549318, 37.89155222168003]}}, {"type": "Feature", "properties": {"speed": 23.471674724199953, "color": "#6a4770"}, "geometry": {"type": "Point", "coordinates": [-122.51682040431119, 37.89133879304618]}}, {"type": "Feature", "properties": {"speed": 22.364297753013865, "color": "#664874"}, "geometry": {"type": "Point", "coordinates": [-122.51685278293294, 37.891132097303846]}}, {"type": "Feature", "properties": {"speed": 21.39238495425397, "color": "#634977"}, "geometry": {"type": "Point", "coordinates": [-122.51688369468432, 37.89093861682988]}}, {"type": "Feature", "properties": {"speed": 20.110948955513617, "color": "#5f4b7b"}, "geometry": {"type": "Point", "coordinates": [-122.51691678026607, 37.89075207767027]}}, {"type": "Feature", "properties": {"speed": 19.07247354593963, "color": "#5b4c7f"}, "geometry": {"type": "Point", "coordinates": [-122.51694944268971, 37.89057731428295]}}, {"type": "Feature", "properties": {"speed": 17.828768399651423, "color": "#574e83"}, "geometry": {"type": "Point", "coordinates": [-122.5169797108483, 37.89041703166]}}, {"type": "Feature", "properties": {"speed": 16.428076445825976, "color": "#525087"}, "geometry": {"type": "Point", "coordinates": [-122.51700849793252, 37.89025637218192]}}, {"type": "Feature", "properties": {"speed": 15.618227978157162, "color": "#4f518a"}, "geometry": {"type": "Point", "coordinates": [-122.51703192641487, 37.89011687227024]}}, {"type": "Feature", "properties": {"speed": 14.640961001768911, "color": "#4c528d"}, "geometry": {"type": "Point", "coordinates": [-122.51705549662042, 37.889981104470074]}}, {"type": "Feature", "properties": {"speed": 13.370959105200715, "color": "#475391"}, "geometry": {"type": "Point", "coordinates": [-122.51708250653715, 37.8898581233482]}}, {"type": "Feature", "properties": {"speed": 11.976728802981306, "color": "#425596"}, "geometry": {"type": "Point", "coordinates": [-122.51712373816052, 37.88974449027277]}}, {"type": "Feature", "properties": {"speed": 10.177116573212095, "color": "#3c579c"}, "geometry": {"type": "Point", "coordinates": [-122.51717351035943, 37.88966326523547]}}, {"type": "Feature", "properties": {"speed": 7.788516989255985, "color": "#345aa3"}, "geometry": {"type": "Point", "coordinates": [-122.51723698220353, 37.88959865717537]}}, {"type": "Feature", "properties": {"speed": 5.779038579203601, "color": "#2d5daa"}, "geometry": {"type": "Point", "coordinates": [-122.51729712803132, 37.88955992794764]}}, {"type": "Feature", "properties": {"speed": 4.713551961543013, "color": "#295ead"}, "geometry": {"type": "Point", "coordinates": [-122.51735645549088, 37.88955049549706]}}]}