{"type": "FeatureCollection", "features": [{"type": "Feature", "properties": {"speed": 12.446401953544017, "color": "#445494"}, "geometry": {"type": "Point", "coordinates": [-122.43845215370283, 37.73163528010766]}}, {"type": "Feature", "properties": {"speed": 12.11285515666414, "color": "#435595"}, "geometry": {"type": "Point", "coordinates": [-122.43858713611414, 37.731635104458384]}}, {"type": "Feature", "properties": {"speed": 10.995306123195846, "color": "#3f5699"}, "geometry": {"type": "Point", "coordinates": [-122.43871957568939, 37.731634867980716]}}, {"type": "Feature", "properties": {"speed": 9.979999542236328, "color": "#3b579c"}, "geometry": {"type": "Point", "coordinates": [-122.43884421612155, 37.73163453033626]}}, {"type": "Feature", "properties": {"speed": 8.630195719701714, "color": "#3759a1"}, "geometry": {"type": "Point", "coordinates": [-122.43894008359725, 37.731634237252614]}}, {"type": "Feature", "properties": {"speed": 5.621530920933484, "color": "#2c5daa"}, "geometry": {"type": "Point", "coordinates": [-122.43900539562283, 37.731634037582324]}}, {"type": "Feature", "properties": {"speed": 4.149802204059726, "color": "#275faf"}, "geometry": {"type": "Point", "coordinates": [-122.43906495349532, 37.731633855503496]}}, {"type": "Feature", "properties": {"speed": 3.111495123521156, "color": "#2360b3"}, "geometry": {"type": "Point", "coordinates": [-122.43910276705849, 37.731633739900815]}}, {"type": "Feature", "properties": {"speed": 1.888528187895726, "color": "#1f61b7"}, "geometry": {"type": "Point", "coordinates": [-122.4391236430002, 37.73163367607941]}}, {"type": "Feature", "properties": {"speed": 1.430815963834096, "color": "#1d62b8"}, "geometry": {"type": "Point", "coordinates": [-122.43913911593837, 37.73163362877593]}}, {"type": "Feature", "properties": {"speed": 1.8094030013260587, "color": "#1f62b7"}, "geometry": {"type": "Point", "coordinates": [-122.43915309821769, 37.73163358602965]}}, {"type": "Feature", "properties": {"speed": 2.0, "color": "#1f61b6"}, "geometry": {"type": "Point", "coordinates": [-122.43917560475616, 37.73163351722323]}}, {"type": "Feature", "properties": {"speed": 2.376495600309587, "color": "#2161b5"}, "geometry": {"type": "Point", "coordinates": [-122.43920507803107, 37.73163342711827]}}, {"type": "Feature", "properties": {"speed": 2.8981081900054666, "color": "#2360b3"}, "geometry": {"type": "Point", "coordinates": [-122.43924317015257, 37.731633310663995]}}, {"type": "Feature", "properties": {"speed": 2.623925660814992, "color": "#2261b4"}, "geometry": {"type": "Point", "coordinates": [-122.43927434727304, 37.73163321535008]}}, {"type": "Feature", "properties": {"speed": 2.272668316098006, "color": "#2061b5"}, "geometry": {"type": "Point", "coordinates": [-122.43930022958193, 37.73163313622334]}}, {"type": "Feature", "properties": {"speed": 2.009999990463257, "color": "#1f61b6"}, "geometry": {"type": "Point", "coordinates": [-122.43932293298496, 37.73163306681506]}}, {"type": "Feature", "properties": {"speed": 1.8820939174226698, "color": "#1f61b7"}, "geometry": {"type": "Point", "coordinates": [-122.43934144584689, 37.731633010218005]}}, {"type": "Feature", "properties": {"speed": 1.8904158775356559, "color": "#1f61b7"}, "geometry": {"type": "Point", "coordinates": [-122.4393577351692, 37.73163296041869]}}, {"type": "Feature", "properties": {"speed": 2.4510487424472585, "color": "#2161b5"}, "geometry": {"type": "Point", "coordinates": [-122.4393812804505, 37.73163288843665]}}, {"type": "Feature", "properties": {"speed": 2.7598865550591083, "color": "#2260b4"}, "geometry": {"type": "Point", "coordinates": [-122.4394068371277, 37.73163281030542]}}, {"type": "Feature", "properties": {"speed": 2.580872584475016, "color": "#2161b4"}, "geometry": {"type": "Point", "coordinates": [-122.43943146351067, 37.73163273501825]}}, {"type": "Feature", "properties": {"speed": 2.677181193963366, "color": "#2260b4"}, "geometry": {"type": "Point", "coordinates": [-122.4394606202133, 37.73163264588111]}}, {"type": "Feature", "properties": {"speed": 2.9700000286102295, "color": "#2360b3"}, "geometry": {"type": "Point", "coordinates": [-122.43949095923364, 37.73163255312942]}}, {"type": "Feature", "properties": {"speed": 2.6253943392823103, "color": "#2261b4"}, "geometry": {"type": "Point", "coordinates": [-122.4395223121506, 37.731632457278074]}}, {"type": "Feature", "properties": {"speed": 2.016583609995715, "color": "#2061b6"}, "geometry": {"type": "Point", "coordinates": [-122.43954893295798, 37.731632375893604]}}, {"type": "Feature", "properties": {"speed": 2.460790075543981, "color": "#2161b5"}, "geometry": {"type": "Point", "coordinates": [-122.43957854837792, 37.73163228535409]}}, {"type": "Feature", "properties": {"speed": 3.1084058141146724, "color": "#2360b3"}, "geometry": {"type": "Point", "coordinates": [-122.43961313518817, 37.731632179616156]}}, {"type": "Feature", "properties": {"speed": 3.9366117276157375, "color": "#265fb0"}, "geometry": {"type": "Point", "coordinates": [-122.43964981664699, 37.731632067474514]}}, {"type": "Feature", "properties": {"speed": 6.445744552755191, "color": "#2f5ca8"}, "geometry": {"type": "Point", "coordinates": [-122.43970538717161, 37.7316318975857]}}, {"type": "Feature", "properties": {"speed": 8.04325583581633, "color": "#355aa3"}, "geometry": {"type": "Point", "coordinates": [-122.4397784348317, 37.731631505697244]}}, {"type": "Feature", "properties": {"speed": 9.531113564171573, "color": "#3a589e"}, "geometry": {"type": "Point", "coordinates": [-122.4398916881952, 37.731630555829824]}}, {"type": "Feature", "properties": {"speed": 10.623921704124996, "color": "#3e579a"}, "geometry": {"type": "Point", "coordinates": [-122.44002770152441, 37.73162940603643]}}, {"type": "Feature", "properties": {"speed": 11.515255511413793, "color": "#415697"}, "geometry": {"type": "Point", "coordinates": [-122.44016332679918, 37.73162825952348]}}, {"type": "Feature", "properties": {"speed": 12.101392215673757, "color": "#435595"}, "geometry": {"type": "Point", "coordinates": [-122.4403008413072, 37.73162709703983]}}, {"type": "Feature", "properties": {"speed": 12.692261895131544, "color": "#455493"}, "geometry": {"type": "Point", "coordinates": [-122.44044821223525, 37.73162585123459]}}, {"type": "Feature", "properties": {"speed": 12.805570688717127, "color": "#455493"}, "geometry": {"type": "Point", "coordinates": [-122.44059593948614, 37.731624602417156]}}, {"type": "Feature", "properties": {"speed": 12.447837612848303, "color": "#445494"}, "geometry": {"type": "Point", "coordinates": [-122.44074175405026, 37.7316233697687]}}, {"type": "Feature", "properties": {"speed": 12.133852466725138, "color": "#435595"}, "geometry": {"type": "Point", "coordinates": [-122.44088335249518, 37.7316222089961]}}, {"type": "Feature", "properties": {"speed": 11.91783833238224, "color": "#425596"}, "geometry": {"type": "Point", "coordinates": [-122.44102687486483, 37.731621112502694]}}, {"type": "Feature", "properties": {"speed": 11.489627414549716, "color": "#415697"}, "geometry": {"type": "Point", "coordinates": [-122.44116027152376, 37.731620121877874]}}, {"type": "Feature", "properties": {"speed": 10.643785963930132, "color": "#3e579a"}, "geometry": {"type": "Point", "coordinates": [-122.44128465457385, 37.73161919818955]}}, {"type": "Feature", "properties": {"speed": 9.685693230746628, "color": "#3a589d"}, "geometry": {"type": "Point", "coordinates": [-122.44139579539926, 37.731618372840096]}}, {"type": "Feature", "properties": {"speed": 8.976250985921487, "color": "#3859a0"}, "geometry": {"type": "Point", "coordinates": [-122.44150403615703, 37.73161756902701]}}, {"type": "Feature", "properties": {"speed": 8.438173258078901, "color": "#3659a1"}, "geometry": {"type": "Point", "coordinates": [-122.44159467897592, 37.73161689589901]}}, {"type": "Feature", "properties": {"speed": 6.502050160271294, "color": "#2f5ca8"}, "geometry": {"type": "Point", "coordinates": [-122.44166147329717, 37.731616399873744]}}, {"type": "Feature", "properties": {"speed": 4.324056749125247, "color": "#285eaf"}, "geometry": {"type": "Point", "coordinates": [-122.44170084719613, 37.73161610747691]}}, {"type": "Feature", "properties": {"speed": 3.1445187603859392, "color": "#2360b3"}, "geometry": {"type": "Point", "coordinates": [-122.44173023292007, 37.731615889253845]}}, {"type": "Feature", "properties": {"speed": 2.5695098335697155, "color": "#2161b4"}, "geometry": {"type": "Point", "coordinates": [-122.44176656816582, 37.73161561942253]}}, {"type": "Feature", "properties": {"speed": 2.3063315581011583, "color": "#2161b5"}, "geometry": {"type": "Point", "coordinates": [-122.44179334661276, 37.731615420561525]}}, {"type": "Feature", "properties": {"speed": 2.0813834045418793, "color": "#2061b6"}, "geometry": {"type": "Point", "coordinates": [-122.441818743775, 37.73161523195815]}}, {"type": "Feature", "properties": {"speed": 2.432331729894285, "color": "#2161b5"}, "geometry": {"type": "Point", "coordinates": [-122.4418455209774, 37.73161503310639]}}, {"type": "Feature", "properties": {"speed": 3.380000114440918, "color": "#2460b2"}, "geometry": {"type": "Point", "coordinates": [-122.44188221348696, 37.73161476062197]}}, {"type": "Feature", "properties": {"speed": 2.9429728045067325, "color": "#2360b3"}, "geometry": {"type": "Point", "coordinates": [-122.44191146241933, 37.73161454341474]}}, {"type": "Feature", "properties": {"speed": 2.413841717332615, "color": "#2161b5"}, "geometry": {"type": "Point", "coordinates": [-122.44192487338145, 37.73161444382281]}}, {"type": "Feature", "properties": {"speed": 4.290333847400709, "color": "#275eaf"}, "geometry": {"type": "Point", "coordinates": [-122.44197228300366, 37.73161409175141]}}, {"type": "Feature", "properties": {"speed": 7.467357254000541, "color": "#335ba4"}, "geometry": {"type": "Point", "coordinates": [-122.44205210252383, 37.73160603805907]}}, {"type": "Feature", "properties": {"speed": 8.569999694824219, "color": "#3659a1"}, "geometry": {"type": "Point", "coordinates": [-122.442145006672, 37.73159311786508]}}, {"type": "Feature", "properties": {"speed": 8.911713218050396, "color": "#3859a0"}, "geometry": {"type": "Point", "coordinates": [-122.44225600753302, 37.731590703073906]}}, {"type": "Feature", "properties": {"speed": 9.8170521176622, "color": "#3b589d"}, "geometry": {"type": "Point", "coordinates": [-122.44238424745491, 37.731586612260976]}}, {"type": "Feature", "properties": {"speed": 10.282294793545915, "color": "#3c579b"}, "geometry": {"type": "Point", "coordinates": [-122.4425048277956, 37.73158696065242]}}, {"type": "Feature", "properties": {"speed": 10.220153825632169, "color": "#3c579b"}, "geometry": {"type": "Point", "coordinates": [-122.44262790911125, 37.73158855620234]}}, {"type": "Feature", "properties": {"speed": 10.796959425664623, "color": "#3e569a"}, "geometry": {"type": "Point", "coordinates": [-122.44276001452204, 37.73159458986653]}}, {"type": "Feature", "properties": {"speed": 11.350000381469727, "color": "#405698"}, "geometry": {"type": "Point", "coordinates": [-122.44288892799378, 37.73160238908712]}}, {"type": "Feature", "properties": {"speed": 11.357737374798752, "color": "#405698"}, "geometry": {"type": "Point", "coordinates": [-122.44301681791839, 37.73160604462498]}}, {"type": "Feature", "properties": {"speed": 11.369999885559082, "color": "#405698"}, "geometry": {"type": "Point", "coordinates": [-122.44314652994518, 37.73161120934023]}}, {"type": "Feature", "properties": {"speed": 11.529511335047449, "color": "#415697"}, "geometry": {"type": "Point", "coordinates": [-122.44327417565046, 37.731605517624295]}}, {"type": "Feature", "properties": {"speed": 11.982980081316557, "color": "#425596"}, "geometry": {"type": "Point", "coordinates": [-122.44340692596707, 37.73159439807673]}}, {"type": "Feature", "properties": {"speed": 12.482880419243582, "color": "#445494"}, "geometry": {"type": "Point", "coordinates": [-122.44354961876284, 37.73158929524026]}}, {"type": "Feature", "properties": {"speed": 13.057728825416723, "color": "#465492"}, "geometry": {"type": "Point", "coordinates": [-122.4437052041618, 37.731587646552775]}}, {"type": "Feature", "properties": {"speed": 13.391988099501726, "color": "#475391"}, "geometry": {"type": "Point", "coordinates": [-122.44385445390294, 37.73158699854615]}}, {"type": "Feature", "properties": {"speed": 13.40999984741211, "color": "#475391"}, "geometry": {"type": "Point", "coordinates": [-122.44400515260463, 37.73158953994301]}}, {"type": "Feature", "properties": {"speed": 13.436607765711615, "color": "#475391"}, "geometry": {"type": "Point", "coordinates": [-122.44415748059244, 37.731587994691665]}}, {"type": "Feature", "properties": {"speed": 13.441163026853804, "color": "#475391"}, "geometry": {"type": "Point", "coordinates": [-122.44430411171206, 37.73158776819105]}}, {"type": "Feature", "properties": {"speed": 13.451613108624091, "color": "#475391"}, "geometry": {"type": "Point", "coordinates": [-122.44445811256905, 37.7315917624989]}}, {"type": "Feature", "properties": {"speed": 13.892518312218444, "color": "#495390"}, "geometry": {"type": "Point", "coordinates": [-122.44461771488315, 37.731588998370405]}}, {"type": "Feature", "properties": {"speed": 14.368499419108305, "color": "#4b528e"}, "geometry": {"type": "Point", "coordinates": [-122.444775538899, 37.731586752401554]}}, {"type": "Feature", "properties": {"speed": 14.324700327187497, "color": "#4a528e"}, "geometry": {"type": "Point", "coordinates": [-122.44494535151988, 37.73158820863758]}}, {"type": "Feature", "properties": {"speed": 14.149999618530273, "color": "#4a528f"}, "geometry": {"type": "Point", "coordinates": [-122.44510872405732, 37.731585611476106]}}, {"type": "Feature", "properties": {"speed": 13.882454319055498, "color": "#495390"}, "geometry": {"type": "Point", "coordinates": [-122.44526438749273, 37.731583783491004]}}, {"type": "Feature", "properties": {"speed": 13.40999984741211, "color": "#475391"}, "geometry": {"type": "Point", "coordinates": [-122.44541342846088, 37.73158202245481]}}, {"type": "Feature", "properties": {"speed": 12.870731654693293, "color": "#455493"}, "geometry": {"type": "Point", "coordinates": [-122.44556461449135, 37.73158157925784]}}, {"type": "Feature", "properties": {"speed": 11.500875889193354, "color": "#415697"}, "geometry": {"type": "Point", "coordinates": [-122.4457027234032, 37.731580287702286]}}, {"type": "Feature", "properties": {"speed": 10.190752737788355, "color": "#3c579c"}, "geometry": {"type": "Point", "coordinates": [-122.44582783193914, 37.73157933147998]}}, {"type": "Feature", "properties": {"speed": 8.772524643929282, "color": "#3759a0"}, "geometry": {"type": "Point", "coordinates": [-122.44592983941672, 37.731585264175266]}}, {"type": "Feature", "properties": {"speed": 7.260770257690869, "color": "#325ba5"}, "geometry": {"type": "Point", "coordinates": [-122.44600931074528, 37.73158869262478]}}, {"type": "Feature", "properties": {"speed": 5.9414253828327945, "color": "#2d5ca9"}, "geometry": {"type": "Point", "coordinates": [-122.4460789520524, 37.73159196910155]}}, {"type": "Feature", "properties": {"speed": 4.844264792193139, "color": "#295ead"}, "geometry": {"type": "Point", "coordinates": [-122.4461421732722, 37.731594950264956]}}, {"type": "Feature", "properties": {"speed": 4.41985079894507, "color": "#285eae"}, "geometry": {"type": "Point", "coordinates": [-122.446195789478, 37.73159179628557]}}, {"type": "Feature", "properties": {"speed": 4.285095499239543, "color": "#275eaf"}, "geometry": {"type": "Point", "coordinates": [-122.4462466725487, 37.7315861938887]}}, {"type": "Feature", "properties": {"speed": 4.2548624980234395, "color": "#275faf"}, "geometry": {"type": "Point", "coordinates": [-122.44629707621519, 37.731583873721945]}}, {"type": "Feature", "properties": {"speed": 3.879275508683058, "color": "#265fb0"}, "geometry": {"type": "Point", "coordinates": [-122.4463460142016, 37.73158151212892]}}, {"type": "Feature", "properties": {"speed": 3.9181611801252614, "color": "#265fb0"}, "geometry": {"type": "Point", "coordinates": [-122.44638967158579, 37.73157959202385]}}, {"type": "Feature", "properties": {"speed": 4.076384477176359, "color": "#275faf"}, "geometry": {"type": "Point", "coordinates": [-122.44643767231611, 37.731576954757095]}}, {"type": "Feature", "properties": {"speed": 3.368569700228419, "color": "#2460b2"}, "geometry": {"type": "Point", "coordinates": [-122.44647576467682, 37.73157761901968]}}, {"type": "Feature", "properties": {"speed": 4.099783668339187, "color": "#275faf"}, "geometry": {"type": "Point", "coordinates": [-122.44651837707129, 37.7315845646575]}}, {"type": "Feature", "properties": {"speed": 6.7425950817301175, "color": "#305ba7"}, "geometry": {"type": "Point", "coordinates": [-122.44658531237582, 37.73159084625176]}}, {"type": "Feature", "properties": {"speed": 8.619249142973679, "color": "#3759a1"}, "geometry": {"type": "Point", "coordinates": [-122.44667668391, 37.73159386600436]}}, {"type": "Feature", "properties": {"speed": 9.79400662918673, "color": "#3b589d"}, "geometry": {"type": "Point", "coordinates": [-122.44679151476, 37.73159782877838]}}, {"type": "Feature", "properties": {"speed": 10.427975353672261, "color": "#3d579b"}, "geometry": {"type": "Point", "coordinates": [-122.4469136927317, 37.731602125738185]}}, {"type": "Feature", "properties": {"speed": 10.716158740013501, "color": "#3e579a"}, "geometry": {"type": "Point", "coordinates": [-122.44704069653767, 37.7316064386751]}}, {"type": "Feature", "properties": {"speed": 11.204969489586489, "color": "#405698"}, "geometry": {"type": "Point", "coordinates": [-122.44717267179009, 37.73160410610025]}}, {"type": "Feature", "properties": {"speed": 12.247361884339659, "color": "#435595"}, "geometry": {"type": "Point", "coordinates": [-122.44731833628404, 37.73159762618219]}}, {"type": "Feature", "properties": {"speed": 12.841063854663302, "color": "#455493"}, "geometry": {"type": "Point", "coordinates": [-122.44746528434155, 37.731595387195625]}}, {"type": "Feature", "properties": {"speed": 13.186439761515896, "color": "#465492"}, "geometry": {"type": "Point", "coordinates": [-122.44761792446054, 37.73159881469195]}}, {"type": "Feature", "properties": {"speed": 13.170189533491731, "color": "#465492"}, "geometry": {"type": "Point", "coordinates": [-122.44777048404781, 37.73160222330712]}}, {"type": "Feature", "properties": {"speed": 13.232602025250603, "color": "#475392"}, "geometry": {"type": "Point", "coordinates": [-122.44791683523918, 37.73160177964817]}}, {"type": "Feature", "properties": {"speed": 13.333971476204269, "color": "#475391"}, "geometry": {"type": "Point", "coordinates": [-122.44806359739093, 37.73160117043247]}}, {"type": "Feature", "properties": {"speed": 13.273850972315845, "color": "#475392"}, "geometry": {"type": "Point", "coordinates": [-122.44820879211117, 37.731600113050774]}}, {"type": "Feature", "properties": {"speed": 13.411332171677211, "color": "#475391"}, "geometry": {"type": "Point", "coordinates": [-122.44837099247526, 37.73160215812174]}}, {"type": "Feature", "properties": {"speed": 12.032749035760954, "color": "#425596"}, "geometry": {"type": "Point", "coordinates": [-122.44853092434032, 37.73160906712472]}}, {"type": "Feature", "properties": {"speed": 10.275097917806727, "color": "#3c579b"}, "geometry": {"type": "Point", "coordinates": [-122.44865187986008, 37.73161013356922]}}, {"type": "Feature", "properties": {"speed": 7.432223629435693, "color": "#325ba5"}, "geometry": {"type": "Point", "coordinates": [-122.4487300217841, 37.73160966022658]}}, {"type": "Feature", "properties": {"speed": 3.1115124837024757, "color": "#2360b3"}, "geometry": {"type": "Point", "coordinates": [-122.44876409704739, 37.73161512815893]}}, {"type": "Feature", "properties": {"speed": 1.590000033378601, "color": "#1e62b8"}, "geometry": {"type": "Point", "coordinates": [-122.44878870607499, 37.731619945049246]}}, {"type": "Feature", "properties": {"speed": 0.877685121342345, "color": "#1c63ba"}, "geometry": {"type": "Point", "coordinates": [-122.44879779417295, 37.73162000816104]}}, {"type": "Feature", "properties": {"speed": 0.0, "color": "#1864bd"}, "geometry": {"type": "Point", "coordinates": [-122.44879779417295, 37.73162000816104]}}, {"type": "Feature", "properties": {"speed": 0.0, "color": "#1864bd"}, "geometry": {"type": "Point", "coordinates": [-122.44879779417295, 37.73162000816104]}}, {"type": "Feature", "properties": {"speed": 0.0, "color": "#1864bd"}, "geometry": {"type": "Point", "coordinates": [-122.44879779417295, 37.73162000816104]}}, {"type": "Feature", "properties": {"speed": 0.0, "color": "#1864bd"}, "geometry": {"type": "Point", "coordinates": [-122.44879779417295, 37.73162000816104]}}, {"type": "Feature", "properties": {"speed": 0.0, "color": "#1864bd"}, "geometry": {"type": "Point", "coordinates": [-122.44879779417295, 37.73162000816104]}}, {"type": "Feature", "properties": {"speed": 0.0, "color": "#1864bd"}, "geometry": {"type": "Point", "coordinates": [-122.44879779417295, 37.73162000816104]}}, {"type": "Feature", "properties": {"speed": 0.11880607561363174, "color": "#1964bc"}, "geometry": {"type": "Point", "coordinates": [-122.44879052467978, 37.73161341914554]}}, {"type": "Feature", "properties": {"speed": 0.17808626259403765, "color": "#1964bc"}, "geometry": {"type": "Point", "coordinates": [-122.448779437805, 37.73160337008324]}}, {"type": "Feature", "properties": {"speed": 0.0, "color": "#1864bd"}, "geometry": {"type": "Point", "coordinates": [-122.448779437805, 37.73160337008324]}}, {"type": "Feature", "properties": {"speed": 0.0, "color": "#1864bd"}, "geometry": {"type": "Point", "coordinates": [-122.448779437805, 37.73160337008324]}}, {"type": "Feature", "properties": {"speed": 0.0, "color": "#1864bd"}, "geometry": {"type": "Point", "coordinates": [-122.448779437805, 37.73160337008324]}}, {"type": "Feature", "properties": {"speed": 0.0, "color": "#1864bd"}, "geometry": {"type": "Point", "coordinates": [-122.448779437805, 37.73160337008324]}}, {"type": "Feature", "properties": {"speed": 0.0, "color": "#1864bd"}, "geometry": {"type": "Point", "coordinates": [-122.448779437805, 37.73160337008324]}}, {"type": "Feature", "properties": {"speed": 0.0, "color": "#1864bd"}, "geometry": {"type": "Point", "coordinates": [-122.448779437805, 37.73160337008324]}}, {"type": "Feature", "properties": {"speed": 0.0, "color": "#1864bd"}, "geometry": {"type": "Point", "coordinates": [-122.448779437805, 37.73160337008324]}}, {"type": "Feature", "properties": {"speed": 0.0, "color": "#1864bd"}, "geometry": {"type": "Point", "coordinates": [-122.448779437805, 37.73160337008324]}}, {"type": "Feature", "properties": {"speed": 0.0, "color": "#1864bd"}, "geometry": {"type": "Point", "coordinates": [-122.448779437805, 37.73160337008324]}}, {"type": "Feature", "properties": {"speed": 0.0, "color": "#1864bd"}, "geometry": {"type": "Point", "coordinates": [-122.448779437805, 37.73160337008324]}}, {"type": "Feature", "properties": {"speed": 0.0, "color": "#1864bd"}, "geometry": {"type": "Point", "coordinates": [-122.448779437805, 37.73160337008324]}}, {"type": "Feature", "properties": {"speed": 0.0, "color": "#1864bd"}, "geometry": {"type": "Point", "coordinates": [-122.448779437805, 37.73160337008324]}}, {"type": "Feature", "properties": {"speed": 0.0, "color": "#1864bd"}, "geometry": {"type": "Point", "coordinates": [-122.448779437805, 37.73160337008324]}}, {"type": "Feature", "properties": {"speed": 0.0, "color": "#1864bd"}, "geometry": {"type": "Point", "coordinates": [-122.448779437805, 37.73160337008324]}}, {"type": "Feature", "properties": {"speed": 0.0, "color": "#1864bd"}, "geometry": {"type": "Point", "coordinates": [-122.448779437805, 37.73160337008324]}}, {"type": "Feature", "properties": {"speed": 0.0, "color": "#1864bd"}, "geometry": {"type": "Point", "coordinates": [-122.448779437805, 37.73160337008324]}}, {"type": "Feature", "properties": {"speed": 0.0, "color": "#1864bd"}, "geometry": {"type": "Point", "coordinates": [-122.448779437805, 37.73160337008324]}}, {"type": "Feature", "properties": {"speed": 0.10279869551548648, "color": "#1964bc"}, "geometry": {"type": "Point", "coordinates": [-122.44877765068182, 37.73159898205757]}}, {"type": "Feature", "properties": {"speed": 0.15930490820539822, "color": "#1964bc"}, "geometry": {"type": "Point", "coordinates": [-122.44877474393923, 37.73159184496638]}}, {"type": "Feature", "properties": {"speed": 0.20869803643425422, "color": "#1964bc"}, "geometry": {"type": "Point", "coordinates": [-122.44877688592294, 37.73159361210295]}}, {"type": "Feature", "properties": {"speed": 0.28962709886472887, "color": "#1963bc"}, "geometry": {"type": "Point", "coordinates": [-122.44877977308113, 37.73159599400845]}}, {"type": "Feature", "properties": {"speed": 0.0, "color": "#1864bd"}, "geometry": {"type": "Point", "coordinates": [-122.44877977308113, 37.73159599400845]}}, {"type": "Feature", "properties": {"speed": 0.0, "color": "#1864bd"}, "geometry": {"type": "Point", "coordinates": [-122.44877977308113, 37.73159599400845]}}, {"type": "Feature", "properties": {"speed": 0.0, "color": "#1864bd"}, "geometry": {"type": "Point", "coordinates": [-122.44877977308113, 37.73159599400845]}}, {"type": "Feature", "properties": {"speed": 0.3678296973263901, "color": "#1a63bc"}, "geometry": {"type": "Point", "coordinates": [-122.44878703331469, 37.731597635020144]}}, {"type": "Feature", "properties": {"speed": 1.8973544652258068, "color": "#1f61b7"}, "geometry": {"type": "Point", "coordinates": [-122.44880901081007, 37.731600625326905]}}, {"type": "Feature", "properties": {"speed": 4.537996729171065, "color": "#285eae"}, "geometry": {"type": "Point", "coordinates": [-122.44885129888935, 37.73160567725819]}}, {"type": "Feature", "properties": {"speed": 7.132477829816622, "color": "#315ba6"}, "geometry": {"type": "Point", "coordinates": [-122.44892736504241, 37.73161434740931]}}, {"type": "Feature", "properties": {"speed": 8.66628365095612, "color": "#3759a1"}, "geometry": {"type": "Point", "coordinates": [-122.44902292594942, 37.73161611087743]}}, {"type": "Feature", "properties": {"speed": 10.516602897138696, "color": "#3d579b"}, "geometry": {"type": "Point", "coordinates": [-122.44914922148216, 37.73161591611586]}}, {"type": "Feature", "properties": {"speed": 13.1899995803833, "color": "#465492"}, "geometry": {"type": "Point", "coordinates": [-122.44929671158654, 37.731613192145026]}}, {"type": "Feature", "properties": {"speed": 13.917513807755917, "color": "#49538f"}, "geometry": {"type": "Point", "coordinates": [-122.44945318898476, 37.73160676441293]}}, {"type": "Feature", "properties": {"speed": 15.195210849335012, "color": "#4d518b"}, "geometry": {"type": "Point", "coordinates": [-122.44962795565354, 37.73159677476663]}}, {"type": "Feature", "properties": {"speed": 14.861300885880267, "color": "#4c518c"}, "geometry": {"type": "Point", "coordinates": [-122.44979872437996, 37.73159585646818]}}, {"type": "Feature", "properties": {"speed": 14.529598008615013, "color": "#4b528d"}, "geometry": {"type": "Point", "coordinates": [-122.44997026994673, 37.73160415803773]}}]}